unitvis/__init__.py
unitvis/io.py
unitvis/plugin.py
unitvis/prompter.py
pytest_unitvis-0.1.0.dist-info/LICENSE
pytest_unitvis-0.1.0.dist-info/METADATA
pytest_unitvis-0.1.0.dist-info/WHEEL
pytest_unitvis-0.1.0.dist-info/entry_points.txt
pytest_unitvis-0.1.0.dist-info/top_level.txt
pytest_unitvis-0.1.0.dist-info/RECORD
