Metadata-Version: 2.1
Name: pytest-unitvis
Version: 0.1.0
Home-page: https://github.com/kongaskristjan/pytest-unitvis
Author: Kristjan Kongas
License: MIT
Classifier: Development Status :: 3 - Alpha
Classifier: License :: OSI Approved :: MIT License
Classifier: Programming Language :: Python :: 3.8
Classifier: Programming Language :: Python :: 3.9
Classifier: Programming Language :: Python :: 3.10
Classifier: Programming Language :: Python :: 3.11
Classifier: Programming Language :: Python :: 3.12
Requires-Python: >=3.8
License-File: LICENSE
Requires-Dist: pytest >=7.0.0
Requires-Dist: plotly >=5.0.0
Requires-Dist: dash >=2.0.0
Requires-Dist: dash-bootstrap-components >=1.0.0
Requires-Dist: pandas >=2.0.0
